cl_ml_tools/__init__.py
cl_ml_tools/master.py
cl_ml_tools/worker.py
cl_ml_tools/common/__init__.py
cl_ml_tools/common/compute_module.py
cl_ml_tools/common/file_storage.py
cl_ml_tools/common/job_repository.py
cl_ml_tools/common/schemas.py
cl_ml_tools/plugins/__init__.py
cl_ml_tools/plugins/image_conversion/__init__.py
cl_ml_tools/plugins/image_conversion/routes.py
cl_ml_tools/plugins/image_conversion/schema.py
cl_ml_tools/plugins/image_conversion/task.py
cl_ml_tools/plugins/image_resize/__init__.py
cl_ml_tools/plugins/image_resize/routes.py
cl_ml_tools/plugins/image_resize/schema.py
cl_ml_tools/plugins/image_resize/task.py
cl_ml_tools-0.2.0.dist-info/licenses/LICENSE
tests/conftest.py
tests/test_schemas.py
cl_ml_tools-0.2.0.dist-info/METADATA
cl_ml_tools-0.2.0.dist-info/WHEEL
cl_ml_tools-0.2.0.dist-info/entry_points.txt
cl_ml_tools-0.2.0.dist-info/top_level.txt
cl_ml_tools-0.2.0.dist-info/RECORD
