Metadata-Version: 2.4
Name: cl_ml_tools
Version: 0.2.0
Summary: Tools for master-worker media processing / ML - provides task plugins, worker runtime, and protocols for job persistence and file storage
Author: Ananda Sarangaram
License: MIT
Keywords: media,ml,processing,worker,master,compute,image
Classifier: Development Status :: 3 - Alpha
Classifier: Intended Audience :: Developers
Classifier: License :: OSI Approved :: MIT License
Classifier: Programming Language :: Python :: 3
Classifier: Programming Language :: Python :: 3.11
Requires-Python: >=3.11
License-File: LICENSE
Requires-Dist: pydantic>=2.0
Provides-Extra: master
Requires-Dist: fastapi>=0.100; extra == "master"
Requires-Dist: python-multipart>=0.0.6; extra == "master"
Provides-Extra: compute
Requires-Dist: Pillow>=10.0; extra == "compute"
Provides-Extra: dev
Requires-Dist: pytest>=7.0; extra == "dev"
Requires-Dist: pytest-asyncio>=0.21; extra == "dev"
Requires-Dist: pytest-cov>=4.0; extra == "dev"
Requires-Dist: httpx>=0.24; extra == "dev"
Provides-Extra: all
Requires-Dist: cl_ml_tools[compute,dev,master]; extra == "all"
Dynamic: license-file
